bcpractice/__init__.py
bcpractice/__main__.py
bcpractice/cli.py
bcpractice/config.py
bcpractice/generator.py
bcpractice/graphs.py
bcpractice/latex.py
bcpractice/pdf.py
bcpractice/topics.py
bcpractice-0.1.1.dist-info/METADATA
bcpractice-0.1.1.dist-info/WHEEL
bcpractice-0.1.1.dist-info/entry_points.txt
bcpractice-0.1.1.dist-info/licenses/LICENSE
bcpractice-0.1.1.dist-info/RECORD
