Metadata-Version: 2.4
Name: bcpractice
Version: 0.1.1
Summary: CLI tool to generate AP BC Calculus practice problems using AI
Project-URL: Homepage, https://github.com/aaravjaichand/bcpractice
Project-URL: Repository, https://github.com/aaravjaichand/bcpractice
Author-email: Aarav Jaichand <aaravai413@gmail.com>
License: MIT
License-File: LICENSE
Keywords: ap,calculus,cli,education,pdf,practice
Classifier: Development Status :: 3 - Alpha
Classifier: Environment :: Console
Classifier: Intended Audience :: Education
Classifier: License :: OSI Approved :: MIT License
Classifier: Programming Language :: Python :: 3
Classifier: Programming Language :: Python :: 3.9
Classifier: Programming Language :: Python :: 3.10
Classifier: Programming Language :: Python :: 3.11
Classifier: Programming Language :: Python :: 3.12
Classifier: Topic :: Education
Requires-Python: >=3.9
Requires-Dist: anthropic>=0.18.0
Requires-Dist: jinja2>=3.1.0
Requires-Dist: openai>=1.0.0
Requires-Dist: questionary>=2.0.0
Requires-Dist: rich>=13.0.0
Requires-Dist: typer>=0.9.0
